odoo/addons/stock_picking_batch_set_quantity/README.rst
odoo/addons/stock_picking_batch_set_quantity/__init__.py
odoo/addons/stock_picking_batch_set_quantity/__manifest__.py
odoo/addons/stock_picking_batch_set_quantity/i18n/it.po
odoo/addons/stock_picking_batch_set_quantity/i18n/stock_picking_batch_set_quantity.pot
odoo/addons/stock_picking_batch_set_quantity/models/__init__.py
odoo/addons/stock_picking_batch_set_quantity/models/stock_move.py
odoo/addons/stock_picking_batch_set_quantity/models/stock_move_line.py
odoo/addons/stock_picking_batch_set_quantity/readme/CONTRIBUTORS.rst
odoo/addons/stock_picking_batch_set_quantity/readme/DESCRIPTION.rst
odoo/addons/stock_picking_batch_set_quantity/readme/USAGE.rst
odoo/addons/stock_picking_batch_set_quantity/static/description/icon.png
odoo/addons/stock_picking_batch_set_quantity/static/description/index.html
odoo/addons/stock_picking_batch_set_quantity/views/stock_picking_batch_views.xml
odoo_addon_stock_picking_batch_set_quantity-15.0.1.1.0.dist-info/METADATA
odoo_addon_stock_picking_batch_set_quantity-15.0.1.1.0.dist-info/WHEEL
odoo_addon_stock_picking_batch_set_quantity-15.0.1.1.0.dist-info/top_level.txt
odoo_addon_stock_picking_batch_set_quantity-15.0.1.1.0.dist-info/RECORD
